waiter/__init__.py
waiter/decorator.py
waiter.py-1.0.0.dist-info/LICENSE
waiter.py-1.0.0.dist-info/METADATA
waiter.py-1.0.0.dist-info/WHEEL
waiter.py-1.0.0.dist-info/top_level.txt
waiter.py-1.0.0.dist-info/RECORD
