Metadata-Version: 2.1
Name: waiter.py
Version: 1.0.0
Summary: A more efficient way of conforming to limits via waiting
Author: depthbomb
Project-URL: Repository, https://github.com/depthbomb/waiter.py
Project-URL: Issues, https://github.com/depthbomb/waiter.py/issues
Project-URL: Changelog, https://github.com/depthbomb/waiter.py/blob/master/CHANGELOG.md
Classifier: Development Status :: 5 - Production/Stable
Classifier: Intended Audience :: Developers
Classifier: License :: OSI Approved :: MIT License
Classifier: Natural Language :: English
Classifier: Programming Language :: Python :: 3
Classifier: Programming Language :: Python :: 3.10
Classifier: Programming Language :: Python :: 3.11
Classifier: Topic :: Software Development
Classifier: Topic :: Software Development :: Libraries
Classifier: Topic :: Software Development :: Libraries :: Python Modules
Classifier: Topic :: Utilities
Requires-Python: >=3.10
License-File: LICENSE
